{"_type":"export","__export_format":4,"__export_date":"2020-06-26T15:31:32.115Z","__export_source":"insomnia.desktop.app:v2020.2.2","resources":[{"_id":"req_7b2a70fb1eb14ba88f59d8815efc5aa7","authentication":{},"body":{},"created":1591854733412,"description":"","headers":[],"isPrivate":false,"metaSortKey":-1592343465806,"method":"GET","modified":1592521789828,"name":"Test server connection","parameters":[],"parentId":"wrk_cd4e4a2ecad54bcab179b19416822315","settingDisableRenderRequestBody":false,"settingEncodeUrl":true,"settingFollowRedirects":"global","settingRebuildPath":true,"settingSendCookies":true,"settingStoreCookies":true,"url":"{{ baseUrl  }}/test-connection","_type":"request"},{"_id":"wrk_cd4e4a2ecad54bcab179b19416822315","created":1591829285880,"description":"","modified":1591829285880,"name":"Farma","parentId":null,"scope":null,"_type":"workspace"},{"_id":"req_e5c37e15640f41a0a058cde6033da485","authentication":{},"body":{"mimeType":"application/json","text":"{\n\t\"email\": \"john_doe@pharmacy.com\",\n\t\"password\": \"123456\"\n}"},"created":1592516700013,"description":"","headers":[{"id":"pair_d99773ff76e449c6ae86447bb76bfde6","name":"Content-Type","value":"application/json"}],"isPrivate":false,"metaSortKey":-1592343607581,"method":"POST","modified":1592845376225,"name":"Create","parameters":[],"parentId":"fld_2b03f4ad2fef458bb35f2014cf3f87cf","settingDisableRenderRequestBody":false,"settingEncodeUrl":true,"settingFollowRedirects":"global","settingRebuildPath":true,"settingSendCookies":true,"settingStoreCookies":true,"url":"{{ baseUrl  }}/sessions","_type":"request"},{"_id":"fld_2b03f4ad2fef458bb35f2014cf3f87cf","created":1592516695694,"description":"","environment":{},"environmentPropertyOrder":null,"metaSortKey":-1592343465781,"modified":1592865808868,"name":"Sessions","parentId":"wrk_cd4e4a2ecad54bcab179b19416822315","_type":"request_group"},{"_id":"req_0c00e72dca55434d9cb467b90333b60b","authentication":{"token":"{{ tokenClient  }}","type":"bearer"},"body":{"mimeType":"application/json","text":"{\n\t\"name\": \"Jonas Doe\",\n\t\"email\": \"{% response 'body', 'req_1f712b21e93a4b87b4f2c18501bc1107', 'b64::JC51c2VyLmVtYWls::46b', 'never' %}\",\n\t\"tel\": \"+0000999999999\"\n}"},"created":1592343696266,"description":"","headers":[{"id":"pair_4cfba5707a9141b2bddd437206715886","name":"Content-Type","value":"application/json"}],"isPrivate":false,"metaSortKey":-1592343696266,"method":"PUT","modified":1592953666436,"name":"Update - Personal Info","parameters":[],"parentId":"fld_3c312628c1cd4d74a341b24a2270619c","settingDisableRenderRequestBody":false,"settingEncodeUrl":true,"settingFollowRedirects":"global","settingRebuildPath":true,"settingSendCookies":true,"settingStoreCookies":true,"url":"{{ baseUrl  }}/users/personal-info","_type":"request"},{"_id":"fld_3c312628c1cd4d74a341b24a2270619c","created":1592343465756,"description":"","environment":{},"environmentPropertyOrder":null,"metaSortKey":-1592343465756,"modified":1592343465756,"name":"User","parentId":"wrk_cd4e4a2ecad54bcab179b19416822315","_type":"request_group"},{"_id":"req_16a5778628a2490bb7f28f42557b44d5","authentication":{"token":"{{ tokenClient  }}","type":"bearer"},"body":{"mimeType":"application/json","text":"{\n\t\"avatar\": null,\n\t\"street\": \"Rua XyZ\",\n\t\"address_details\": \"sobrado azul\",\n\t\"building_number\": \"999\",\n\t\"uf\": \"SC\",\n\t\"city\": \"Florianopolis\",\n\t\"zip_code\": \"1199199\"\n}"},"created":1592343717238,"description":"","headers":[{"id":"pair_4cfba5707a9141b2bddd437206715886","name":"Content-Type","value":"application/json"}],"isPrivate":false,"metaSortKey":-1592343661341.5,"method":"PUT","modified":1592953673379,"name":"Update - Address","parameters":[],"parentId":"fld_3c312628c1cd4d74a341b24a2270619c","settingDisableRenderRequestBody":false,"settingEncodeUrl":true,"settingFollowRedirects":"global","settingRebuildPath":true,"settingSendCookies":true,"settingStoreCookies":true,"url":"{{ baseUrl  }}/users/personal-info","_type":"request"},{"_id":"req_09adac0d40024b3787d4563c4ffb19f8","authentication":{"token":"{{ tokenClient  }}","type":"bearer"},"body":{},"created":1592343588745,"description":"","headers":[],"isPrivate":false,"metaSortKey":-1592343588745,"method":"DELETE","modified":1592865674462,"name":"Delete","parameters":[],"parentId":"fld_3c312628c1cd4d74a341b24a2270619c","settingDisableRenderRequestBody":false,"settingEncodeUrl":true,"settingFollowRedirects":"global","settingRebuildPath":true,"settingSendCookies":true,"settingStoreCookies":true,"url":"{{ baseUrl  }}/users","_type":"request"},{"_id":"req_c6c2535bdbeb4049bc38791570064ad8","authentication":{"token":"","type":"bearer"},"body":{"mimeType":"application/json","text":"{\n\t\"name\": \"John Doe\",\n\t\"email\": \"john_doe_{% now 'unix', '' %}@client.com\",\n\t\"tel\": \"1111999999999\",\n\t\"password\": \"123456\",\n\t\"avatar\": null,\n\t\"street\": \"Rua XyZ\",\n\t\"address_details\": \"sobrado azul\",\n\t\"building_number\": \"999\",\n\t\"uf\": \"SC\",\n\t\"city\": \"Florianopolis\",\n\t\"zip_code\": \"1199199\",\n\t\"cpf\": \"11199911199\"\n}"},"created":1592343626417,"description":"","headers":[{"id":"pair_d99773ff76e449c6ae86447bb76bfde6","name":"Content-Type","value":"application/json"}],"isPrivate":false,"metaSortKey":-1592343626417,"method":"POST","modified":1592865538208,"name":"Create","parameters":[],"parentId":"fld_4f2d783ee120470898ee4784c1818694","settingDisableRenderRequestBody":false,"settingEncodeUrl":true,"settingFollowRedirects":"global","settingRebuildPath":true,"settingSendCookies":true,"settingStoreCookies":true,"url":"{{ baseUrl  }}/users/client","_type":"request"},{"_id":"fld_4f2d783ee120470898ee4784c1818694","created":1592343470373,"description":"","environment":{},"environmentPropertyOrder":null,"metaSortKey":-1592099099584,"modified":1592343473524,"name":"Client","parentId":"wrk_cd4e4a2ecad54bcab179b19416822315","_type":"request_group"},{"_id":"req_017c4703c06d4725862bacc2fcda2218","authentication":{"token":"{{ tokenClient  }}","type":"bearer"},"body":{"mimeType":"application/json","text":"{\n\t\"cpf\": \"11199911122\"\n}"},"created":1592517408781,"description":"","headers":[{"id":"pair_d99773ff76e449c6ae86447bb76bfde6","name":"Content-Type","value":"application/json"}],"isPrivate":false,"metaSortKey":-1592343616999,"method":"PUT","modified":1592953686127,"name":"Update","parameters":[],"parentId":"fld_4f2d783ee120470898ee4784c1818694","settingDisableRenderRequestBody":false,"settingEncodeUrl":true,"settingFollowRedirects":"global","settingRebuildPath":true,"settingSendCookies":true,"settingStoreCookies":true,"url":"{{ baseUrl  }}/users/client","_type":"request"},{"_id":"req_7011fec40d844f50a9f14023dedf7d4b","authentication":{},"body":{},"created":1592517414056,"description":"","headers":[],"isPrivate":false,"metaSortKey":-1592343626417,"method":"GET","modified":1592953718367,"name":"Index","parameters":[{"description":"","disabled":false,"id":"pair_8298a5b818fb4e26b5d674831153d3ac","name":"q","value":"J"}],"parentId":"fld_6785e3a68518441f81e9c9dea816c483","settingDisableRenderRequestBody":false,"settingEncodeUrl":true,"settingFollowRedirects":"global","settingRebuildPath":true,"settingSendCookies":true,"settingStoreCookies":true,"url":"{{ baseUrl  }}/users/pharmacy","_type":"request"},{"_id":"fld_6785e3a68518441f81e9c9dea816c483","created":1592517414042,"description":"","environment":{},"environmentPropertyOrder":null,"metaSortKey":-1592038008041,"modified":1592517414042,"name":"Pharmacy","parentId":"wrk_cd4e4a2ecad54bcab179b19416822315","_type":"request_group"},{"_id":"req_010771c37a03401f8ebdb74968edc1db","authentication":{},"body":{},"created":1592517951669,"description":"","headers":[],"isPrivate":false,"metaSortKey":-1592343624062.5,"method":"GET","modified":1592865216005,"name":"Show","parameters":[],"parentId":"fld_6785e3a68518441f81e9c9dea816c483","settingDisableRenderRequestBody":false,"settingEncodeUrl":true,"settingFollowRedirects":"global","settingRebuildPath":true,"settingSendCookies":true,"settingStoreCookies":true,"url":"{{ baseUrl  }}/users/pharmacy/{% response 'body', 'req_7011fec40d844f50a9f14023dedf7d4b', 'b64::JFswXS5pZA==::46b', 'always' %}","_type":"request"},{"_id":"req_346e632bb6194c1cadddf919dca90aad","authentication":{},"body":{"mimeType":"application/json","text":"{\n\t\"name\": \"John Doe\",\n\t\"email\": \"john_doe_{% now 'unix', '' %}@pharmacy.com\",\n\t\"tel\": \"1111999999999\",\n\t\"password\": \"123456\",\n\t\"avatar\": null,\n\t\"street\": \"Rua XyZ\",\n\t\"address_details\": \"sobrado azul\",\n\t\"building_number\": \"999\",\n\t\"uf\": \"SC\",\n\t\"city\": \"Florianopolis\",\n\t\"zip_code\": \"1199199\",\n\t\"cnpj\": \"11199911199\",\n\t\"description\": \"Uma farmácia normal\"\n}"},"created":1592517948955,"description":"","headers":[{"id":"pair_d99773ff76e449c6ae86447bb76bfde6","name":"Content-Type","value":"application/json"}],"isPrivate":false,"metaSortKey":-1592343621708,"method":"POST","modified":1592865484576,"name":"Create","parameters":[],"parentId":"fld_6785e3a68518441f81e9c9dea816c483","settingDisableRenderRequestBody":false,"settingEncodeUrl":true,"settingFollowRedirects":"global","settingRebuildPath":true,"settingSendCookies":true,"settingStoreCookies":true,"url":"{{ baseUrl  }}/users/pharmacy","_type":"request"},{"_id":"req_d69cab1ab488433392db3242fd0474da","authentication":{"token":"{{ tokenPharmacy  }}","type":"bearer"},"body":{"mimeType":"application/json","text":"{\n\t\"cnpj\": \"11199911122\",\n\t\"description\": \"Uma farmácia especial\"\n}"},"created":1592517414075,"description":"","headers":[{"id":"pair_d99773ff76e449c6ae86447bb76bfde6","name":"Content-Type","value":"application/json"}],"isPrivate":false,"metaSortKey":-1592343616999,"method":"PUT","modified":1592953756874,"name":"Update","parameters":[],"parentId":"fld_6785e3a68518441f81e9c9dea816c483","settingDisableRenderRequestBody":false,"settingEncodeUrl":true,"settingFollowRedirects":"global","settingRebuildPath":true,"settingSendCookies":true,"settingStoreCookies":true,"url":"{{ baseUrl  }}/users/pharmacy/","_type":"request"},{"_id":"req_0f729afa337c40379c9e012a18620720","authentication":{},"body":{},"created":1592857159813,"description":"","headers":[],"isPrivate":false,"metaSortKey":-1592343626417,"method":"GET","modified":1592860517282,"name":"Index","parameters":[{"description":"","disabled":true,"id":"pair_8298a5b818fb4e26b5d674831153d3ac","name":"q","value":"j"}],"parentId":"fld_92253acfe49c4eb592564f0d7462e913","settingDisableRenderRequestBody":false,"settingEncodeUrl":true,"settingFollowRedirects":"global","settingRebuildPath":true,"settingSendCookies":true,"settingStoreCookies":true,"url":"{{ baseUrl  }}/products","_type":"request"},{"_id":"fld_92253acfe49c4eb592564f0d7462e913","created":1592857159797,"description":"","environment":{},"environmentPropertyOrder":null,"metaSortKey":-1592007462269.5,"modified":1592857159797,"name":"Products","parentId":"wrk_cd4e4a2ecad54bcab179b19416822315","_type":"request_group"},{"_id":"req_224b0f4e1ab043e6801eb6fb96a6854a","authentication":{},"body":{},"created":1592857159846,"description":"","headers":[],"isPrivate":false,"metaSortKey":-1592343624062.5,"method":"GET","modified":1592859941489,"name":"Show","parameters":[],"parentId":"fld_92253acfe49c4eb592564f0d7462e913","settingDisableRenderRequestBody":false,"settingEncodeUrl":true,"settingFollowRedirects":"global","settingRebuildPath":true,"settingSendCookies":true,"settingStoreCookies":true,"url":"{{ baseUrl  }}/products/{% response 'body', 'req_0f729afa337c40379c9e012a18620720', 'b64::JFswXS5pZA==::46b', 'always' %}","_type":"request"},{"_id":"req_fa18a881dfc04ffd93583c8bc1d8f4ef","authentication":{"token":"{{ tokenPharmacy  }}","type":"bearer"},"body":{"mimeType":"application/json","text":"{\n\t\"name\": \"remédio pra dor de cabeça\",\n\t\"description\": \"melhora a dor de cabeça\",\n\t\"needs_recipe\": true\n}"},"created":1592857159841,"description":"","headers":[{"id":"pair_d99773ff76e449c6ae86447bb76bfde6","name":"Content-Type","value":"application/json"}],"isPrivate":false,"metaSortKey":-1592343621708,"method":"POST","modified":1592857419484,"name":"Create","parameters":[],"parentId":"fld_92253acfe49c4eb592564f0d7462e913","settingDisableRenderRequestBody":false,"settingEncodeUrl":true,"settingFollowRedirects":"global","settingRebuildPath":true,"settingSendCookies":true,"settingStoreCookies":true,"url":"{{ baseUrl  }}/products","_type":"request"},{"_id":"req_e5b352f0294d417183feb27d46701dd1","authentication":{"token":"{{ tokenPharmacy  }}","type":"bearer"},"body":{"mimeType":"application/json","text":"{\n\t\"name\": \"remédio para colica intestinal\",\n\t\"description\": \"remédio para a barriga parar de doer \",\n\t\"needs_recipe\": false\n}"},"created":1592857159832,"description":"","headers":[{"id":"pair_d99773ff76e449c6ae86447bb76bfde6","name":"Content-Type","value":"application/json"}],"isPrivate":false,"metaSortKey":-1592343616999,"method":"PUT","modified":1592859947639,"name":"Update","parameters":[],"parentId":"fld_92253acfe49c4eb592564f0d7462e913","settingDisableRenderRequestBody":false,"settingEncodeUrl":true,"settingFollowRedirects":"global","settingRebuildPath":true,"settingSendCookies":true,"settingStoreCookies":true,"url":"{{ baseUrl  }}/products/{% response 'body', 'req_0f729afa337c40379c9e012a18620720', 'b64::JFswXS5pZA==::46b', 'always' %}","_type":"request"},{"_id":"req_5893752c6d0f472090d673c5455b9340","authentication":{"token":"{{ tokenPharmacy  }}","type":"bearer"},"body":{},"created":1592857174556,"description":"","headers":[],"isPrivate":false,"metaSortKey":-1592343616949,"method":"DELETE","modified":1592859958540,"name":"Delete","parameters":[],"parentId":"fld_92253acfe49c4eb592564f0d7462e913","settingDisableRenderRequestBody":false,"settingEncodeUrl":true,"settingFollowRedirects":"global","settingRebuildPath":true,"settingSendCookies":true,"settingStoreCookies":true,"url":"{{ baseUrl  }}/products/{% response 'body', 'req_0f729afa337c40379c9e012a18620720', 'b64::JFswXS5pZA==::46b', 'always' %}","_type":"request"},{"_id":"req_dd3dec28927f4666a93b56e5a78f4940","authentication":{},"body":{},"created":1592857187522,"description":"","headers":[],"isPrivate":false,"metaSortKey":-1592343626417,"method":"GET","modified":1592870644570,"name":"Index","parameters":[{"description":"","disabled":true,"id":"pair_8298a5b818fb4e26b5d674831153d3ac","name":"q","value":"j"}],"parentId":"fld_e6ab32adfb33446c92c212ea94c1c30a","settingDisableRenderRequestBody":false,"settingEncodeUrl":true,"settingFollowRedirects":"global","settingRebuildPath":true,"settingSendCookies":true,"settingStoreCookies":true,"url":"{{ baseUrl  }}/pharmacy/{% response 'body', 'req_2116608a052d4c4887da60ae0e72714a', 'b64::JC51c2VyLmlk::46b', 'never' %}/stocks","_type":"request"},{"_id":"fld_e6ab32adfb33446c92c212ea94c1c30a","created":1592857187506,"description":"","environment":{},"environmentPropertyOrder":null,"metaSortKey":-1591992189383.75,"modified":1592857187506,"name":"Stocks","parentId":"wrk_cd4e4a2ecad54bcab179b19416822315","_type":"request_group"},{"_id":"req_858814679132424dbc5a376189559178","authentication":{},"body":{},"created":1592857187557,"description":"","headers":[],"isPrivate":false,"metaSortKey":-1592343624062.5,"method":"GET","modified":1592870670573,"name":"Show","parameters":[],"parentId":"fld_e6ab32adfb33446c92c212ea94c1c30a","settingDisableRenderRequestBody":false,"settingEncodeUrl":true,"settingFollowRedirects":"global","settingRebuildPath":true,"settingSendCookies":true,"settingStoreCookies":true,"url":"{{ baseUrl  }}/pharmacy/{% response 'body', 'req_2116608a052d4c4887da60ae0e72714a', 'b64::JC51c2VyLmlk::46b', 'never' %}/stocks/{% response 'body', 'req_dd3dec28927f4666a93b56e5a78f4940', 'b64::JFswXS5wcm9kdWN0X2lk::46b', 'always' %}","_type":"request"},{"_id":"req_3fc93c356e794a21a4d75da49939342d","authentication":{"token":"{{ tokenPharmacy  }}","type":"bearer"},"body":{"mimeType":"application/json","text":"{\n\t\"product_id\": \"{% response 'body', 'req_0f729afa337c40379c9e012a18620720', 'b64::JFswXS5pZA==::46b', 'always' %}\",\n\t\"price\": 19.99,\n\t\"quantity\": 500\n}"},"created":1592857187551,"description":"","headers":[{"id":"pair_d99773ff76e449c6ae86447bb76bfde6","name":"Content-Type","value":"application/json"}],"isPrivate":false,"metaSortKey":-1592343621708,"method":"POST","modified":1592871375766,"name":"Create","parameters":[],"parentId":"fld_e6ab32adfb33446c92c212ea94c1c30a","settingDisableRenderRequestBody":false,"settingEncodeUrl":true,"settingFollowRedirects":"global","settingRebuildPath":true,"settingSendCookies":true,"settingStoreCookies":true,"url":"{{ baseUrl  }}/stocks","_type":"request"},{"_id":"req_ad518a3221da4775bdd84a3ed99ee5b6","authentication":{"token":"{{ tokenPharmacy  }}","type":"bearer"},"body":{"mimeType":"application/json","text":"{\n\t\"price\": 22.99,\n\t\"quantity\": 250\n}"},"created":1592857187542,"description":"","headers":[{"id":"pair_d99773ff76e449c6ae86447bb76bfde6","name":"Content-Type","value":"application/json"}],"isPrivate":false,"metaSortKey":-1592343616999,"method":"PUT","modified":1592869248610,"name":"Update","parameters":[],"parentId":"fld_e6ab32adfb33446c92c212ea94c1c30a","settingDisableRenderRequestBody":false,"settingEncodeUrl":true,"settingFollowRedirects":"global","settingRebuildPath":true,"settingSendCookies":true,"settingStoreCookies":true,"url":"{{ baseUrl  }}/stocks/{% response 'body', 'req_dd3dec28927f4666a93b56e5a78f4940', 'b64::JFswXS5wcm9kdWN0X2lk::46b', 'always' %}","_type":"request"},{"_id":"req_9d15527ba6864749a2f29dd490ed3063","authentication":{"token":"{{ tokenPharmacy  }}","type":"bearer"},"body":{},"created":1592857187562,"description":"","headers":[],"isPrivate":false,"metaSortKey":-1592343616949,"method":"DELETE","modified":1592869562300,"name":"Delete","parameters":[],"parentId":"fld_e6ab32adfb33446c92c212ea94c1c30a","settingDisableRenderRequestBody":false,"settingEncodeUrl":true,"settingFollowRedirects":"global","settingRebuildPath":true,"settingSendCookies":true,"settingStoreCookies":true,"url":"{{ baseUrl  }}/stocks/{% response 'body', 'req_dd3dec28927f4666a93b56e5a78f4940', 'b64::JFswXS5wcm9kdWN0X2lk::46b', 'always' %}","_type":"request"},{"_id":"req_2116608a052d4c4887da60ae0e72714a","authentication":{},"body":{"mimeType":"application/json","text":"{\n\t\"email\": \"{% response 'body', 'req_346e632bb6194c1cadddf919dca90aad', 'b64::JC5lbWFpbA==::46b', 'no-history' %}\",\n\t\"password\": \"123456\"\n}"},"created":1592860025421,"description":"","headers":[{"id":"pair_d99773ff76e449c6ae86447bb76bfde6","name":"Content-Type","value":"application/json"}],"isPrivate":false,"metaSortKey":-1592343598163,"method":"POST","modified":1592865631723,"name":"Login Pharmacy","parameters":[],"parentId":"fld_1a873ae9f3f24f0987b4ef9e93ade6c5","settingDisableRenderRequestBody":false,"settingEncodeUrl":true,"settingFollowRedirects":"global","settingRebuildPath":true,"settingSendCookies":true,"settingStoreCookies":true,"url":"{{ baseUrl  }}/sessions","_type":"request"},{"_id":"fld_1a873ae9f3f24f0987b4ef9e93ade6c5","created":1592860008490,"description":"","environment":{},"environmentPropertyOrder":null,"metaSortKey":-1591976916448,"modified":1592860496709,"name":"Aux requests - Do not change it","parentId":"wrk_cd4e4a2ecad54bcab179b19416822315","_type":"request_group"},{"_id":"req_1f712b21e93a4b87b4f2c18501bc1107","authentication":{},"body":{"mimeType":"application/json","text":"{\n\t\"email\": \"{% response 'body', 'req_c6c2535bdbeb4049bc38791570064ad8', 'b64::JC5lbWFpbA==::46b', 'no-history' %}\",\n\t\"password\": \"123456\"\n}"},"created":1592860034824,"description":"","headers":[{"id":"pair_d99773ff76e449c6ae86447bb76bfde6","name":"Content-Type","value":"application/json"}],"isPrivate":false,"metaSortKey":-1592343593454,"method":"POST","modified":1592865698270,"name":"Login Client","parameters":[],"parentId":"fld_1a873ae9f3f24f0987b4ef9e93ade6c5","settingDisableRenderRequestBody":false,"settingEncodeUrl":true,"settingFollowRedirects":"global","settingRebuildPath":true,"settingSendCookies":true,"settingStoreCookies":true,"url":"{{ baseUrl  }}/sessions","_type":"request"},{"_id":"env_d5f45d39fa9c751fe76d29bda343ba1da75bd881","color":null,"created":1591829286380,"data":{},"dataPropertyOrder":{},"isPrivate":false,"metaSortKey":1591829286380,"modified":1591829311755,"name":"Base Environment","parentId":"wrk_cd4e4a2ecad54bcab179b19416822315","_type":"environment"},{"_id":"jar_d5f45d39fa9c751fe76d29bda343ba1da75bd881","cookies":[],"created":1591829286425,"modified":1591829286425,"name":"Default Jar","parentId":"wrk_cd4e4a2ecad54bcab179b19416822315","_type":"cookie_jar"},{"_id":"spc_399fda71eb554888b33de0677a8e25fc","contentType":"yaml","contents":"","created":1591829285889,"fileName":"Farma","modified":1591829285889,"parentId":"wrk_cd4e4a2ecad54bcab179b19416822315","_type":"api_spec"},{"_id":"env_74d9ebcc7a364f4b9b89c4c915d6aca8","color":"#ff8000","created":1591829314095,"data":{"baseUrl":"http://localhost:3333","tokenClient":"{% response 'body', 'req_1f712b21e93a4b87b4f2c18501bc1107', 'b64::JC50b2tlbg==::46b', 'always' %}","tokenPharmacy":"{% response 'body', 'req_2116608a052d4c4887da60ae0e72714a', 'b64::JC50b2tlbg==::46b', 'always' %}"},"dataPropertyOrder":{"&":["baseUrl","tokenClient","tokenPharmacy"]},"isPrivate":false,"metaSortKey":1591829314095,"modified":1592865687039,"name":"Dev","parentId":"env_d5f45d39fa9c751fe76d29bda343ba1da75bd881","_type":"environment"}]}